pytest_k8s/__init__.py
pytest_k8s/cleanup.py
pytest_k8s/config.py
pytest_k8s/plugin.py
pytest_k8s/py.typed
pytest_k8s/fixtures/__init__.py
pytest_k8s/fixtures/k8s_client.py
pytest_k8s/fixtures/k8s_cluster.py
pytest_k8s/kind/__init__.py
pytest_k8s/kind/cluster.py
pytest_k8s/kind/cluster_manager.py
pytest_k8s/kind/command_runner.py
pytest_k8s/kind/config.py
pytest_k8s/kind/errors.py
pytest_k8s/kind/loggers.py
pytest_k8s/kind/streaming.py
pytest_k8s-1.0.0.dist-info/METADATA
pytest_k8s-1.0.0.dist-info/WHEEL
pytest_k8s-1.0.0.dist-info/entry_points.txt
pytest_k8s-1.0.0.dist-info/RECORD
