Metadata-Version: 2.4
Name: pytest-k8s
Version: 1.0.0
Summary: Kubernetes-based testing for pytest
Author-email: Thomas Jack Carroll <thomas.jack.carroll@gmail.com>
Classifier: Framework :: Pytest
Requires-Python: >=3.13
Requires-Dist: kubernetes>=33.1.0
Requires-Dist: pytest>=8.4.1
Requires-Dist: pyyaml>=6.0
Provides-Extra: build
Requires-Dist: uv~=0.7.12; extra == 'build'
